Metadata-Version: 1.1
Name: danixcalculator
Version: 0.0.1
Summary: Basic Calculator 2 numbers
Home-page: UNKNOWN
Author: Danix25
Author-email: UNKNOWN
License: MIT
Platform: UNKNOWN
Classifier: Development Status :: 5 - Production/Stable
Classifier: Intended Audience :: Education
Classifier: Operating System :: Microsoft :: Windows :: Windows 10
Classifier: License :: OSI Approved :: MIT License
Classifier: Programming Language :: Python :: 3
